README.md
nester.py
setup.py
nester_eslamturki.egg-info/PKG-INFO
nester_eslamturki.egg-info/SOURCES.txt
nester_eslamturki.egg-info/dependency_links.txt
nester_eslamturki.egg-info/top_level.txt